docker_swarm_plugin/__init__.py
docker_swarm_plugin/main.py
docker_swarm_plugin/models/__init__.py
docker_swarm_plugin/models/events.py
docker_swarm_plugin/models/service_models.py
docker_swarm_plugin/models/sql_models.py
docker_swarm_plugin/models/swarm_snapshot.py
docker_swarm_plugin/repositories/base_repository.py
docker_swarm_plugin/repositories/docker_swarm_repository.py
docker_swarm_plugin/services/__init__.py
docker_swarm_plugin/services/service_config_service.py
docker_swarm_plugin/services/cluster_config_service/cluster_config_service.py
docker_swarm_plugin/services/cluster_config_service/cluster_config_service_docker_impl.py
ambient_docker_swarm_plugin-1.8.0.dist-info/METADATA
ambient_docker_swarm_plugin-1.8.0.dist-info/WHEEL
ambient_docker_swarm_plugin-1.8.0.dist-info/top_level.txt
ambient_docker_swarm_plugin-1.8.0.dist-info/RECORD
