Metadata-Version: 2.4
Name: ambient_docker_swarm_plugin
Version: 1.8.0
Summary: An AmbientEdgeServer plugin for managing docker swarms
Author-email: Jose Catarino <jose@ambientlabscomputing.com>
License: MIT
Requires-Python: >=3.7
Requires-Dist: pydantic<=2.7.4
Requires-Dist: ambient_backend_api_client>=3.0.1
Requires-Dist: apluggy>=1.0.3
